pynexusx/__init__.py
pynexusx/main.py
pynexusx-1.1.1.dist-info/licenses/LICENSE
pynexusx-1.1.1.dist-info/METADATA
pynexusx-1.1.1.dist-info/WHEEL
pynexusx-1.1.1.dist-info/entry_points.txt
pynexusx-1.1.1.dist-info/top_level.txt
pynexusx-1.1.1.dist-info/RECORD
